appconfig/__init__.py
appconfig/environ_paths.py
appconfig/main.py
py_appconfig-0.1.2.dist-info/LICENSE
py_appconfig-0.1.2.dist-info/WHEEL
py_appconfig-0.1.2.dist-info/METADATA
py_appconfig-0.1.2.dist-info/RECORD
