Metadata-Version: 2.1
Name: py-appconfig
Version: 0.1.2
Summary: Persistent configuration storage for python applications
Home-page: https://github.com/anujdatar/py-appconfig
License: MIT
Author: Anuj Datar
Author-email: anuj.datar@gmail.com
Requires-Python: >=3.7,<4.0
Classifier: License :: OSI Approved :: MIT License
Classifier: Programming Language :: Python :: 3
Classifier: Programming Language :: Python :: 3.10
Classifier: Programming Language :: Python :: 3.7
Classifier: Programming Language :: Python :: 3.8
Classifier: Programming Language :: Python :: 3.9
